earningsfeed/__init__.py
earningsfeed/client.py
earningsfeed/exceptions.py
earningsfeed/models.py
earningsfeed/py.typed
earningsfeed-0.1.1.dist-info/METADATA
earningsfeed-0.1.1.dist-info/WHEEL
earningsfeed-0.1.1.dist-info/RECORD
