Metadata-Version: 2.4
Name: earningsfeed
Version: 0.1.1
Summary: Official Python SDK for the Earnings Feed API - SEC filings, insider transactions, and institutional holdings
Project-URL: Homepage, https://earningsfeed.com
Project-URL: Documentation, https://earningsfeed.com/api/docs
Project-URL: Repository, https://github.com/earningsfeed/earningsfeed-python
Project-URL: Issues, https://github.com/earningsfeed/earningsfeed-python/issues
Project-URL: PyPI, https://pypi.org/project/earningsfeed/
Author-email: Earnings Feed <contact@earningsfeed.com>
License-Expression: MIT
Keywords: 10-K,10-Q,13F,8-K,api,edgar,filings,finance,form-4,insider-trading,institutional-holdings,sec
Classifier: Development Status :: 4 - Beta
Classifier: Intended Audience :: Developers
Classifier: Intended Audience :: Financial and Insurance Industry
Classifier: License :: OSI Approved :: MIT License
Classifier: Operating System :: OS Independent
Classifier: Programming Language :: Python :: 3
Classifier: Programming Language :: Python :: 3.9
Classifier: Programming Language :: Python :: 3.10
Classifier: Programming Language :: Python :: 3.11
Classifier: Programming Language :: Python :: 3.12
Classifier: Programming Language :: Python :: 3.13
Classifier: Topic :: Office/Business :: Financial
Classifier: Topic :: Software Development :: Libraries :: Python Modules
Classifier: Typing :: Typed
Requires-Python: >=3.9
Requires-Dist: eval-type-backport>=0.2.0; python_version < '3.10'
Requires-Dist: httpx>=0.25.0
Requires-Dist: pydantic>=2.0.0
Provides-Extra: dev
Requires-Dist: mypy>=1.0.0; extra == 'dev'
Requires-Dist: pytest-asyncio>=0.21.0; extra == 'dev'
Requires-Dist: pytest>=7.0.0; extra == 'dev'
Requires-Dist: respx>=0.20.0; extra == 'dev'
Requires-Dist: ruff>=0.1.0; extra == 'dev'
